[
  {
    "weight": {
      "imperial": "8 - 20",
      "metric": "4 - 9"
    },
    "id": "raga",
    "name": "Ragamuffin",
    "cfa_url": "http://cfa.org/Breeds/BreedsKthruR/Ragamuffin.aspx",
    "vetstreet_url": "http://www.vetstreet.com/cats/ragamuffin",
    "vcahospitals_url": "https://vcahospitals.com/know-your-pet/cat-breeds/ragamuffin",
    "temperament": "Affectionate, Friendly, Gentle, Calm",
    "origin": "United States",
    "country_codes": "US",
    "country_code": "US",
    "description": "The Ragamuffin is calm, even tempered and gets along well with all family members. Changes in routine generally do not upset her. She is an ideal companion for those in apartments, and with children due to her patient nature.",
    "life_span": "12 - 16",
    "indoor": 0,
    "lap": 1,
    "alt_names": "",
    "adaptability": 5,
    "affection_level": 5,
    "child_friendly": 4,
    "dog_friendly": 5,
    "energy_level": 3,
    "grooming": 3,
    "health_issues": 3,
    "intelligence": 5,
    "shedding_level": 3,
    "social_needs": 3,
    "stranger_friendly": 5,
    "vocalisation": 1,
    "experimental": 0,
    "hairless": 0,
    "natural": 0,
    "rare": 0,
    "rex": 0,
    "suppressed_tail": 0,
    "short_legs": 0,
    "wikipedia_url": "https://en.wikipedia.org/wiki/Ragamuffin_cat",
    "hypoallergenic": 0,
    "reference_image_id": "SMuZx-bFM",
    "image": {
      "id": "SMuZx-bFM",
      "width": 3000,
      "height": 2000,
      "url": "https://cdn2.thecatapi.com/images/SMuZx-bFM.jpg"
    }
  },
  {
    "weight": {
      "imperial": "12 - 20",
      "metric": "5 - 9"
    },
    "id": "ragd",
    "name": "Ragdoll",
    "cfa_url": "http://cfa.org/Breeds/BreedsKthruR/Ragdoll.aspx",
    "vetstreet_url": "http://www.vetstreet.com/cats/ragdoll",
    "vcahospitals_url": "https://vcahospitals.com/know-your-pet/cat-breeds/ragdoll",
    "temperament": "Affectionate, Friendly, Gentle, Quiet, Easygoing",
    "origin": "United States",
    "country_codes": "US",
    "country_code": "US",
    "description": "Ragdolls love their people, greeting them at the door, following them around the house, and leaping into a lap or snuggling in bed whenever given the chance. They are the epitome of a lap cat, enjoy being carried and collapsing into the arms of anyone who holds them.",
    "life_span": "12 - 17",
    "indoor": 0,
    "lap": 1,
    "alt_names": "Rag doll",
    "adaptability": 5,
    "affection_level": 5,
    "child_friendly": 4,
    "dog_friendly": 5,
    "energy_level": 3,
    "grooming": 2,
    "health_issues": 3,
    "intelligence": 3,
    "shedding_level": 3,
    "social_needs": 5,
    "stranger_friendly": 3,
    "vocalisation": 1,
    "experimental": 0,
    "hairless": 0,
    "natural": 0,
    "rare": 0,
    "rex": 0,
    "suppressed_tail": 0,
    "short_legs": 0,
    "wikipedia_url": "https://en.wikipedia.org/wiki/Ragdoll",
    "hypoallergenic": 0,
    "reference_image_id": "oGefY4YoG",
    "image": {
      "id": "oGefY4YoG",
      "width": 768,
      "height": 1024,
      "url": "https://cdn2.thecatapi.com/images/oGefY4YoG.jpg"
    }
  },
  {
    "weight": {
      "imperial": "5 - 11",
      "metric": "2 - 5"
    },
    "id": "rblu",
    "name": "Russian Blue",
    "cfa_url": "http://cfa.org/Breeds/BreedsKthruR/RussianBlue.aspx",
    "vetstreet_url": "http://www.vetstreet.com/cats/russian-blue-nebelung",
    "vcahospitals_url": "https://vcahospitals.com/know-your-pet/cat-breeds/russian-blue",
    "temperament": "Active, Dependent, Easy Going, Gentle, Intelligent, Loyal, Playful, Quiet",
    "origin": "Russia",
    "country_codes": "RU",
    "country_code": "RU",
    "description": "Russian Blues are very loving and reserved. They do not like noisy households but they do like to play and can be quite active when outdoors. They bond very closely with their owner and are known to be compatible with other pets.",
    "life_span": "10 - 16",
    "indoor": 0,
    "lap": 1,
    "alt_names": "Archangel Blue, Archangel Cat",
    "adaptability": 3,
    "affection_level": 3,
    "child_friendly": 3,
    "dog_friendly": 3,
    "energy_level": 3,
    "grooming": 3,
    "health_issues": 1,
    "intelligence": 3,
    "shedding_level": 3,
    "social_needs": 3,
    "stranger_friendly": 1,
    "vocalisation": 1,
    "experimental": 0,
    "hairless": 0,
    "natural": 1,
    "rare": 0,
    "rex": 0,
    "suppressed_tail": 0,
    "short_legs": 0,
    "wikipedia_url": "https://en.wikipedia.org/wiki/Russian_Blue",
    "hypoallergenic": 1,
    "reference_image_id": "Rhj-JsTLP",
    "image": {
      "id": "Rhj-JsTLP",
      "width": 1280,
      "height": 853,
      "url": "https://cdn2.thecatapi.com/images/Rhj-JsTLP.jpg"
    }
  },
  {
    "weight": {
      "imperial": "8 - 25",
      "metric": "4 - 11"
    },
    "id": "sava",
    "name": "Savannah",
    "vetstreet_url": "http://www.vetstreet.com/cats/savannah",
    "temperament": "Curious, Social, Intelligent, Loyal, Outgoing, Adventurous, Affectionate",
    "origin": "United States",
    "country_codes": "US",
    "country_code": "US",
    "description": "Savannah is the feline version of a dog. Actively seeking social interaction, they are given to pouting if left out. Remaining kitten-like through life. Profoundly loyal to immediate family members whilst questioning the presence of strangers. Making excellent companions that are loyal, intelligent and eager to be involved.",
    "life_span": "17 - 20",
    "indoor": 0,
    "alt_names": "",
    "adaptability": 5,
    "affection_level": 5,
    "child_friendly": 4,
    "dog_friendly": 5,
    "energy_level": 5,
    "grooming": 1,
    "health_issues": 1,
    "intelligence": 5,
    "shedding_level": 3,
    "social_needs": 5,
    "stranger_friendly": 5,
    "vocalisation": 1,
    "experimental": 1,
    "hairless": 0,
    "natural": 0,
    "rare": 0,
    "rex": 0,
    "suppressed_tail": 0,
    "short_legs": 0,
    "wikipedia_url": "https://en.wikipedia.org/wiki/Savannah_cat",
    "hypoallergenic": 0,
    "reference_image_id": "a8nIYvs6S",
    "image": {
      "id": "a8nIYvs6S",
      "width": 850,
      "height": 1100,
      "url": "https://cdn2.thecatapi.com/images/a8nIYvs6S.jpg"
    }
  },
  {
    "weight": {
      "imperial": "5 - 11",
      "metric": "2 - 5"
    },
    "id": "sfol",
    "name": "Scottish Fold",
    "cfa_url": "http://cfa.org/Breeds/BreedsSthruT/ScottishFold.aspx",
    "vetstreet_url": "http://www.vetstreet.com/cats/scottish-fold-highland-fold",
    "vcahospitals_url": "https://vcahospitals.com/know-your-pet/cat-breeds/scottish-fold",
    "temperament": "Affectionate, Intelligent, Loyal, Playful, Social, Sweet, Loving",
    "origin": "United Kingdom",
    "country_codes": "GB",
    "country_code": "GB",
    "description": "The Scottish Fold is a sweet, charming breed. She is an easy cat to live with and to care for. She is affectionate and is comfortable with all members of her family. Her tail should be handled gently. Folds are known for sleeping on their backs, and for sitting with their legs stretched out and their paws on their belly. This is called the \"Buddha Position\".",
    "life_span": "11 - 14",
    "indoor": 0,
    "alt_names": "Scot Fold",
    "adaptability": 5,
    "affection_level": 5,
    "child_friendly": 4,
    "dog_friendly": 5,
    "energy_level": 3,
    "grooming": 1,
    "health_issues": 4,
    "intelligence": 3,
    "shedding_level": 3,
    "social_needs": 3,
    "stranger_friendly": 3,
    "vocalisation": 1,
    "experimental": 0,
    "hairless": 0,
    "natural": 0,
    "rare": 0,
    "rex": 0,
    "suppressed_tail": 0,
    "short_legs": 0,
    "wikipedia_url": "https://en.wikipedia.org/wiki/Scottish_Fold",
    "hypoallergenic": 0,
    "reference_image_id": "o9t0LDcsa",
    "image": {
      "id": "o9t0LDcsa",
      "width": 1920,
      "height": 1440,
      "url": "https://cdn2.thecatapi.com/images/o9t0LDcsa.jpg"
    }
  },
  {
    "weight": {
      "imperial": "6 - 16",
      "metric": "3 - 7"
    },
    "id": "srex",
    "name": "Selkirk Rex",
    "cfa_url": "http://cfa.org/Breeds/BreedsSthruT/SelkirkRex.aspx",
    "vetstreet_url": "http://www.vetstreet.com/cats/selkirk-rex",
    "vcahospitals_url": "https://vcahospitals.com/know-your-pet/cat-breeds/selkirk-rex",
    "temperament": "Active, Affectionate, Dependent, Gentle, Patient, Playful, Quiet, Social",
    "origin": "United States",
    "country_codes": "US",
    "country_code": "US",
    "description": "The Selkirk Rex is an incredibly patient, loving, and tolerant breed. The Selkirk also has a silly side and is sometimes described as clownish. She loves being a lap cat and will be happy to chat with you in a quiet voice if you talk to her. ",
    "life_span": "14 - 15",
    "indoor": 0,
    "lap": 1,
    "alt_names": "Shepherd Cat",
    "adaptability": 5,
    "affection_level": 5,
    "child_friendly": 4,
    "dog_friendly": 5,
    "energy_level": 3,
    "grooming": 2,
    "health_issues": 4,
    "intelligence": 3,
    "shedding_level": 1,
    "social_needs": 3,
    "stranger_friendly": 3,
    "vocalisation": 3,
    "experimental": 0,
    "hairless": 0,
    "natural": 0,
    "rare": 0,
    "rex": 1,
    "suppressed_tail": 0,
    "short_legs": 0,
    "wikipedia_url": "https://en.wikipedia.org/wiki/Selkirk_Rex",
    "hypoallergenic": 1,
    "reference_image_id": "II9dOZmrw",
    "image": {
      "id": "II9dOZmrw",
      "width": 1920,
      "height": 902,
      "url": "https://cdn2.thecatapi.com/images/II9dOZmrw.jpg"
    }
  },
  {
    "weight": {
      "imperial": "8 - 15",
      "metric": "4 - 7"
    },
    "id": "siam",
    "name": "Siamese",
    "cfa_url": "http://cfa.org/Breeds/BreedsSthruT/Siamese.aspx",
    "vetstreet_url": "http://www.vetstreet.com/cats/siamese",
    "vcahospitals_url": "https://vcahospitals.com/know-your-pet/cat-breeds/siamese",
    "temperament": "Active, Agile, Clever, Sociable, Loving, Energetic",
    "origin": "Thailand",
    "country_codes": "TH",
    "country_code": "TH",
    "description": "While Siamese cats are extremely fond of their people, they will follow you around and supervise your every move, being talkative and opinionated. They are a demanding and social cat, that do not like being left alone for long periods.",
    "life_span": "12 - 15",
    "indoor": 0,
    "lap": 1,
    "alt_names": "Siam, Thai Cat",
    "adaptability": 5,
    "affection_level": 5,
    "child_friendly": 4,
    "dog_friendly": 5,
    "energy_level": 5,
    "grooming": 1,
    "health_issues": 1,
    "intelligence": 5,
    "shedding_level": 2,
    "social_needs": 5,
    "stranger_friendly": 5,
    "vocalisation": 5,
    "experimental": 0,
    "hairless": 0,
    "natural": 0,
    "rare": 0,
    "rex": 0,
    "suppressed_tail": 0,
    "short_legs": 0,
    "wikipedia_url": "https://en.wikipedia.org/wiki/Siamese_(cat)",
    "hypoallergenic": 1,
    "reference_image_id": "ai6Jps4sx",
    "image": {
      "id": "ai6Jps4sx",
      "width": 1110,
      "height": 811,
      "url": "https://cdn2.thecatapi.com/images/ai6Jps4sx.jpg"
    }
  },
  {
    "weight": {
      "imperial": "8 - 16",
      "metric": "4 - 7"
    },
    "id": "sibe",
    "name": "Siberian",
    "cfa_url": "http://cfa.org/Breeds/BreedsSthruT/Siberian.aspx",
    "vetstreet_url": "http://www.vetstreet.com/cats/siberian",
    "vcahospitals_url": "https://vcahospitals.com/know-your-pet/cat-breeds/siberian",
    "temperament": "Curious, Intelligent, Loyal, Sweet, Agile, Playful, Affectionate",
    "origin": "Russia",
    "country_codes": "RU",
    "country_code": "RU",
    "description": "The Siberians dog like temperament and affection makes the ideal lap cat and will live quite happily indoors. Very agile and powerful, the Siberian cat can easily leap and reach high places, including the tops of refrigerators and even doors. ",
    "life_span": "12 - 15",
    "indoor": 0,
    "lap": 1,
    "alt_names": "Moscow Semi-longhair, HairSiberian Forest Cat",
    "adaptability": 5,
    "affection_level": 5,
    "child_friendly": 4,
    "dog_friendly": 5,
    "energy_level": 5,
    "grooming": 2,
    "health_issues": 2,
    "intelligence": 5,
    "shedding_level": 3,
    "social_needs": 4,
    "stranger_friendly": 3,
    "vocalisation": 1,
    "experimental": 0,
    "hairless": 0,
    "natural": 1,
    "rare": 0,
    "rex": 0,
    "suppressed_tail": 0,
    "short_legs": 0,
    "wikipedia_url": "https://en.wikipedia.org/wiki/Siberian_(cat)",
    "hypoallergenic": 1,
    "reference_image_id": "3bkZAjRh1",
    "image": {
      "id": "3bkZAjRh1",
      "width": 4232,
      "height": 2560,
      "url": "https://cdn2.thecatapi.com/images/3bkZAjRh1.jpg"
    }
  },
  {
    "weight": {
      "imperial": "5 - 8",
      "metric": "2 - 4"
    },
    "id": "sing",
    "name": "Singapura",
    "cfa_url": "http://cfa.org/Breeds/BreedsSthruT/Singapura.aspx",
    "vetstreet_url": "http://www.vetstreet.com/cats/singapura",
    "vcahospitals_url": "https://vcahospitals.com/know-your-pet/cat-breeds/singapura",
    "temperament": "Affectionate, Curious, Easy Going, Intelligent, Interactive, Lively, Loyal",
    "origin": "Singapore",
    "country_codes": "SP",
    "country_code": "SP",
    "description": "The Singapura is usually cautious when it comes to meeting new people, but loves attention from his family so much that she sometimes has the reputation of being a pest. This is a highly active, curious and affectionate cat. She may be small, but she knows she’s in charge",
    "life_span": "12 - 15",
    "indoor": 0,
    "lap": 1,
    "alt_names": "Drain Cat, Kucinta, Pura",
    "adaptability": 5,
    "affection_level": 5,
    "child_friendly": 4,
    "dog_friendly": 5,
    "energy_level": 5,
    "grooming": 1,
    "health_issues": 1,
    "intelligence": 5,
    "shedding_level": 3,
    "social_needs": 5,
    "stranger_friendly": 5,
    "vocalisation": 1,
    "experimental": 0,
    "hairless": 0,
    "natural": 0,
    "rare": 0,
    "rex": 0,
    "suppressed_tail": 0,
    "short_legs": 0,
    "wikipedia_url": "https://en.wikipedia.org/wiki/Singapura_(cat)",
    "hypoallergenic": 0,
    "reference_image_id": "Qtncp2nRe",
    "image": {
      "id": "Qtncp2nRe",
      "width": 1080,
      "height": 1350,
      "url": "https://cdn2.thecatapi.com/images/Qtncp2nRe.jpg"
    }
  },
  {
    "weight": {
      "imperial": "7 - 12",
      "metric": "3 - 5"
    },
    "id": "snow",
    "name": "Snowshoe",
    "temperament": "Affectionate, Social, Intelligent, Sweet-tempered",
    "origin": "United States",
    "country_codes": "US",
    "country_code": "US",
    "description": "The Snowshoe is a vibrant, energetic, affectionate and intelligent cat. They love being around people which makes them ideal for families, and becomes unhappy when left alone for long periods of time. Usually attaching themselves to one person, they do whatever they can to get your attention.",
    "life_span": "14 - 19",
    "indoor": 0,
    "lap": 1,
    "alt_names": "",
    "adaptability": 5,
    "affection_level": 5,
    "child_friendly": 4,
    "dog_friendly": 5,
    "energy_level": 4,
    "grooming": 3,
    "health_issues": 1,
    "intelligence": 5,
    "shedding_level": 3,
    "social_needs": 4,
    "stranger_friendly": 4,
    "vocalisation": 5,
    "experimental": 0,
    "hairless": 0,
    "natural": 0,
    "rare": 0,
    "rex": 0,
    "suppressed_tail": 0,
    "short_legs": 0,
    "wikipedia_url": "https://en.wikipedia.org/wiki/Snowshoe_(cat)",
    "hypoallergenic": 0,
    "reference_image_id": "MK-sYESvO",
    "image": {
      "id": "MK-sYESvO",
      "width": 1170,
      "height": 750,
      "url": "https://cdn2.thecatapi.com/images/MK-sYESvO.jpg"
    }
  },
  {
    "weight": {
      "imperial": "6 - 12",
      "metric": "3 - 5"
    },
    "id": "soma",
    "name": "Somali",
    "cfa_url": "http://cfa.org/Breeds/BreedsSthruT/Somali.aspx",
    "vetstreet_url": "http://www.vetstreet.com/cats/somali",
    "vcahospitals_url": "https://vcahospitals.com/know-your-pet/cat-breeds/somali",
    "temperament": "Mischievous, Tenacious, Intelligent, Affectionate, Gentle, Interactive, Loyal",
    "origin": "Somalia",
    "country_codes": "SO",
    "country_code": "SO",
    "description": "The Somali lives life to the fullest. He climbs higher, jumps farther, plays harder. Nothing escapes the notice of this highly intelligent and inquisitive cat. Somalis love the company of humans and other animals.",
    "life_span": "12 - 16",
    "indoor": 0,
    "alt_names": "Fox Cat, Long-Haired Abyssinian",
    "adaptability": 5,
    "affection_level": 5,
    "child_friendly": 3,
    "dog_friendly": 4,
    "energy_level": 5,
    "grooming": 3,
    "health_issues": 2,
    "intelligence": 5,
    "shedding_level": 4,
    "social_needs": 5,
    "stranger_friendly": 5,
    "vocalisation": 1,
    "experimental": 0,
    "hairless": 0,
    "natural": 0,
    "rare": 0,
    "rex": 0,
    "suppressed_tail": 0,
    "short_legs": 0,
    "wikipedia_url": "https://en.wikipedia.org/wiki/Somali_(cat)",
    "hypoallergenic": 0,
    "reference_image_id": "EPF2ejNS0",
    "image": {
      "id": "EPF2ejNS0",
      "width": 850,
      "height": 1008,
      "url": "https://cdn2.thecatapi.com/images/EPF2ejNS0.jpg"
    }
  },
  {
    "weight": {
      "imperial": "6 - 12",
      "metric": "3 - 5"
    },
    "id": "sphy",
    "name": "Sphynx",
    "cfa_url": "http://cfa.org/Breeds/BreedsSthruT/Sphynx.aspx",
    "vetstreet_url": "http://www.vetstreet.com/cats/sphynx",
    "vcahospitals_url": "https://vcahospitals.com/know-your-pet/cat-breeds/sphynx",
    "temperament": "Loyal, Inquisitive, Friendly, Quiet, Gentle",
    "origin": "Canada",
    "country_codes": "CA",
    "country_code": "CA",
    "description": "The Sphynx is an intelligent, inquisitive, extremely friendly people-oriented breed. Sphynx commonly greet their owners  at the front door, with obvious excitement and happiness. She has an unexpected sense of humor that is often at odds with her dour expression.",
    "life_span": "12 - 14",
    "indoor": 0,
    "lap": 1,
    "alt_names": "Canadian Hairless, Canadian Sphynx",
    "adaptability": 5,
    "affection_level": 5,
    "child_friendly": 4,
    "dog_friendly": 5,
    "energy_level": 3,
    "grooming": 2,
    "health_issues": 4,
    "intelligence": 5,
    "shedding_level": 1,
    "social_needs": 5,
    "stranger_friendly": 5,
    "vocalisation": 5,
    "experimental": 0,
    "hairless": 1,
    "natural": 0,
    "rare": 1,
    "rex": 0,
    "suppressed_tail": 0,
    "short_legs": 0,
    "wikipedia_url": "https://en.wikipedia.org/wiki/Sphynx_(cat)",
    "hypoallergenic": 1,
    "reference_image_id": "BDb8ZXb1v",
    "image": {
      "id": "BDb8ZXb1v",
      "width": 1600,
      "height": 1067,
      "url": "https://cdn2.thecatapi.com/images/BDb8ZXb1v.jpg"
    }
  },
  {
    "weight": {
      "imperial": "6 - 12",
      "metric": "3 - 5"
    },
    "id": "tonk",
    "name": "Tonkinese",
    "cfa_url": "http://cfa.org/Breeds/BreedsSthruT/Tonkinese.aspx",
    "vetstreet_url": "http://www.vetstreet.com/cats/tonkinese",
    "vcahospitals_url": "https://vcahospitals.com/know-your-pet/cat-breeds/tonkinese",
    "temperament": "Curious, Intelligent, Social, Lively, Outgoing, Playful, Affectionate",
    "origin": "Canada",
    "country_codes": "CA",
    "country_code": "CA",
    "description": "Intelligent and generous with their affection, a Tonkinese will supervise all activities with curiosity. Loving, social, active, playful, yet content to be a lap cat",
    "life_span": "14 - 16",
    "indoor": 0,
    "lap": 1,
    "alt_names": "Tonk",
    "adaptability": 5,
    "affection_level": 5,
    "child_friendly": 4,
    "dog_friendly": 5,
    "energy_level": 5,
    "grooming": 1,
    "health_issues": 1,
    "intelligence": 5,
    "shedding_level": 3,
    "social_needs": 5,
    "stranger_friendly": 5,
    "vocalisation": 5,
    "experimental": 0,
    "hairless": 0,
    "natural": 0,
    "rare": 0,
    "rex": 0,
    "suppressed_tail": 0,
    "short_legs": 0,
    "wikipedia_url": "https://en.wikipedia.org/wiki/Tonkinese_(cat)",
    "hypoallergenic": 0,
    "reference_image_id": "KBroiVNCM",
    "image": {
      "id": "KBroiVNCM",
      "width": 1080,
      "height": 1080,
      "url": "https://cdn2.thecatapi.com/images/KBroiVNCM.jpg"
    }
  },
  {
    "weight": {
      "imperial": "7 - 15",
      "metric": "3 - 7"
    },
    "id": "toyg",
    "name": "Toyger",
    "vetstreet_url": "http://www.vetstreet.com/cats/toyger",
    "temperament": "Playful, Social, Intelligent",
    "origin": "United States",
    "country_codes": "US",
    "country_code": "US",
    "description": "The Toyger has a sweet, calm personality and is generally friendly. He's outgoing enough to walk on a leash, energetic enough to play fetch and other interactive games, and confident enough to get along with other cats and friendly dogs.",
    "life_span": "12 - 15",
    "indoor": 0,
    "lap": 1,
    "alt_names": "",
    "adaptability": 5,
    "affection_level": 5,
    "child_friendly": 4,
    "dog_friendly": 5,
    "energy_level": 5,
    "grooming": 1,
    "health_issues": 2,
    "intelligence": 5,
    "shedding_level": 3,
    "social_needs": 3,
    "stranger_friendly": 5,
    "vocalisation": 5,
    "experimental": 0,
    "hairless": 0,
    "natural": 0,
    "rare": 0,
    "rex": 0,
    "suppressed_tail": 0,
    "short_legs": 0,
    "wikipedia_url": "https://en.wikipedia.org/wiki/Toyger",
    "hypoallergenic": 0,
    "reference_image_id": "O3F3_S1XN",
    "image": {
      "id": "O3F3_S1XN",
      "width": 1080,
      "height": 1080,
      "url": "https://cdn2.thecatapi.com/images/O3F3_S1XN.jpg"
    }
  },
  {
    "weight": {
      "imperial": "5 - 10",
      "metric": "2 - 5"
    },
    "id": "tang",
    "name": "Turkish Angora",
    "cfa_url": "http://cfa.org/Breeds/BreedsSthruT/TurkishAngora.aspx",
    "vetstreet_url": "http://www.vetstreet.com/cats/turkish-angora",
    "vcahospitals_url": "https://vcahospitals.com/know-your-pet/cat-breeds/turkish-angora",
    "temperament": "Affectionate, Agile, Clever, Gentle, Intelligent, Playful, Social",
    "origin": "Turkey",
    "country_codes": "TR",
    "country_code": "TR",
    "description": "This is a smart and intelligent cat which bonds well with humans. With its affectionate and playful personality the Angora is a top choice for families. The Angora gets along great with other pets in the home, but it will make clear who is in charge, and who the house belongs to",
    "life_span": "15 - 18",
    "indoor": 0,
    "alt_names": "Ankara",
    "adaptability": 5,
    "affection_level": 5,
    "child_friendly": 4,
    "dog_friendly": 5,
    "energy_level": 5,
    "grooming": 2,
    "health_issues": 2,
    "intelligence": 5,
    "shedding_level": 2,
    "social_needs": 5,
    "stranger_friendly": 5,
    "vocalisation": 3,
    "experimental": 0,
    "hairless": 0,
    "natural": 1,
    "rare": 0,
    "rex": 0,
    "suppressed_tail": 0,
    "short_legs": 0,
    "wikipedia_url": "https://en.wikipedia.org/wiki/Turkish_Angora",
    "hypoallergenic": 0,
    "reference_image_id": "7CGV6WVXq",
    "image": {
      "id": "7CGV6WVXq",
      "width": 736,
      "height": 1104,
      "url": "https://cdn2.thecatapi.com/images/7CGV6WVXq.jpg"
    }
  },
  {
    "weight": {
      "imperial": "7 - 20",
      "metric": "3 - 9"
    },
    "id": "tvan",
    "name": "Turkish Van",
    "cfa_url": "http://cfa.org/Breeds/BreedsSthruT/TurkishVan.aspx",
    "vetstreet_url": "http://www.vetstreet.com/cats/turkish-van",
    "vcahospitals_url": "https://vcahospitals.com/know-your-pet/cat-breeds/turkish-van",
    "temperament": "Agile, Intelligent, Loyal, Playful, Energetic",
    "origin": "Turkey",
    "country_codes": "TR",
    "country_code": "TR",
    "description": "While the Turkish Van loves to jump and climb, play with toys, retrieve and play chase, she is is big and ungainly; this is one cat who doesn’t always land on his feet. While not much of a lap cat, the Van will be happy to cuddle next to you and sleep in your bed. ",
    "life_span": "12 - 17",
    "indoor": 0,
    "alt_names": "Turkish Cat, Swimming cat",
    "adaptability": 5,
    "affection_level": 5,
    "child_friendly": 4,
    "dog_friendly": 5,
    "energy_level": 5,
    "grooming": 2,
    "health_issues": 1,
    "intelligence": 5,
    "shedding_level": 3,
    "social_needs": 4,
    "stranger_friendly": 4,
    "vocalisation": 5,
    "experimental": 0,
    "hairless": 0,
    "natural": 1,
    "rare": 0,
    "rex": 0,
    "suppressed_tail": 0,
    "short_legs": 0,
    "wikipedia_url": "https://en.wikipedia.org/wiki/Turkish_Van",
    "hypoallergenic": 0,
    "reference_image_id": "sxIXJax6h",
    "image": {
      "id": "sxIXJax6h",
      "width": 960,
      "height": 1280,
      "url": "https://cdn2.thecatapi.com/images/sxIXJax6h.jpg"
    }
  },
  {
    "weight": {
      "imperial": "12 - 18",
      "metric": "5 - 8"
    },
    "id": "ycho",
    "name": "York Chocolate",
    "temperament": "Playful, Social, Intelligent, Curious, Friendly",
    "origin": "United States",
    "country_codes": "US",
    "country_code": "US",
    "description": "York Chocolate cats are known to be true lap cats with a sweet temperament. They love to be cuddled and petted. Their curious nature makes them follow you all the time and participate in almost everything you do, even if it's related to water: unlike many other cats, York Chocolates love it.",
    "life_span": "13 - 15",
    "indoor": 0,
    "lap": 1,
    "alt_names": "York",
    "adaptability": 5,
    "affection_level": 5,
    "child_friendly": 4,
    "dog_friendly": 5,
    "energy_level": 5,
    "grooming": 3,
    "health_issues": 1,
    "intelligence": 5,
    "shedding_level": 3,
    "social_needs": 4,
    "stranger_friendly": 4,
    "vocalisation": 5,
    "experimental": 0,
    "hairless": 0,
    "natural": 0,
    "rare": 0,
    "rex": 0,
    "suppressed_tail": 0,
    "short_legs": 0,
    "wikipedia_url": "https://en.wikipedia.org/wiki/York_Chocolate",
    "hypoallergenic": 0,
    "reference_image_id": "0SxW2SQ_S",
    "image": {
      "id": "0SxW2SQ_S",
      "width": 800,
      "height": 1203,
      "url": "https://cdn2.thecatapi.com/images/0SxW2SQ_S.jpg"
    }
  }
]
